modempay/__init__.py
modempay/error.py
modempay/main.py
modempay/resources/__init__.py
modempay/resources/balance.py
modempay/resources/base.py
modempay/resources/customer.py
modempay/resources/payment_intent.py
modempay/resources/sub_account.py
modempay/resources/transaction.py
modempay/resources/transfer.py
modempay/resources/webhook.py
modempay/types/__init__.py
modempay/types/balance.py
modempay/types/customer.py
modempay/types/payment_intent.py
modempay/types/sub_account.py
modempay/types/transaction.py
modempay/types/transfer.py
modempay/types/type.py
modempay/types/webhook.py
modempay-1.0.4.dist-info/METADATA
modempay-1.0.4.dist-info/WHEEL
modempay-1.0.4.dist-info/top_level.txt
modempay-1.0.4.dist-info/RECORD
